{
  "project_info": {
    "project_number": "295317152666",
    "project_id": "ainmont-6cd05",
    "storage_bucket": "ainmont-6cd05.appspot.com"
  },
  "client": [
    {
      "client_info": {
        "mobilesdk_app_id": "1:295317152666:android:ffa60395d5ba69df9a9023",
        "android_client_info": {
          "package_name": "com.example.anime_mont_test"
        }
      },
      "oauth_client": [
        {
          "client_id": "295317152666-4u8m01drmov2etr8nerq1l0v6a2usait.apps.googleusercontent.com",
          "client_type": 1,
          "android_info": {
            "package_name": "com.example.anime_mont_test",
            "certificate_hash": "4d1309373a9ff67c1f578433d455b4fab5561ecc"
          }
        },
        {
          "client_id": "295317152666-qkm03oe0b0pv7n64ia9klegqp1h41cat.apps.googleusercontent.com",
          "client_type": 3
        }
      ],
      "api_key": [
        {
          "current_key": "AIzaSyBqe3Vcx8gX4k-U7eQzOFBKODwLzFAqGKA"
        }
      ],
      "services": {
        "appinvite_service": {
          "other_platform_oauth_client": [
            {
              "client_id": "295317152666-qkm03oe0b0pv7n64ia9klegqp1h41cat.apps.googleusercontent.com",
              "client_type": 3
            }
          ]
        }
      }
    }
  ],
  "configuration_version": "1"
}